ShenduYouquRengongzhinengShizhanXiangmuHeji/README.md
ShenduYouquRengongzhinengShizhanXiangmuHeji/__init__.py
ShenduYouquRengongzhinengShizhanXiangmuHeji/__main__.py
ShenduYouquRengongzhinengShizhanXiangmuHeji/file.pdf
ShenduYouquRengongzhinengShizhanXiangmuHeji/index.html
shendu_youqu_rengongzhineng_shizhan_xiangmu_heji-2024.3.3.0.dist-info/METADATA
shendu_youqu_rengongzhineng_shizhan_xiangmu_heji-2024.3.3.0.dist-info/WHEEL
shendu_youqu_rengongzhineng_shizhan_xiangmu_heji-2024.3.3.0.dist-info/entry_points.txt
shendu_youqu_rengongzhineng_shizhan_xiangmu_heji-2024.3.3.0.dist-info/top_level.txt
shendu_youqu_rengongzhineng_shizhan_xiangmu_heji-2024.3.3.0.dist-info/RECORD
